MANIFEST.in
README.rst
setup.py
deps/cytoolz-0.9.0.1-cp35-cp35m-win32.whl
deps/cytoolz-0.9.0.1-cp35-cp35m-win_amd64.whl
deps/cytoolz-0.9.0.1-cp36-cp36m-win32.whl
deps/cytoolz-0.9.0.1-cp36-cp36m-win_amd64.whl
deps/cytoolz-0.9.0.1-cp37-cp37m-win32.whl
deps/cytoolz-0.9.0.1-cp37-cp37m-win_amd64.whl
deps/hidapi-0.7.99.post21-cp37-cp37m-win32.whl
deps/hidapi-0.7.99.post21-cp37-cp37m-win_amd64.whl
deps/ledgerblue-0.1.18-py3-none-any.whl
deps/lru_dict-1.1.6-cp35-cp35m-win32.whl
deps/lru_dict-1.1.6-cp35-cp35m-win_amd64.whl
deps/lru_dict-1.1.6-cp36-cp36m-win32.whl
deps/lru_dict-1.1.6-cp36-cp36m-win_amd64.whl
deps/lru_dict-1.1.6-cp37-cp37m-win32.whl
deps/lru_dict-1.1.6-cp37-cp37m-win_amd64.whl
deps/pysha3-1.0.2-cp37-cp37m-win32.whl
deps/pysha3-1.0.2-cp37-cp37m-win_amd64.whl
devise/__init__.py
devise/base.py
devise/config.py
devise/ledger.py
devise.egg-info/PKG-INFO
devise.egg-info/SOURCES.txt
devise.egg-info/dependency_links.txt
devise.egg-info/requires.txt
devise.egg-info/top_level.txt
devise/abi/AuditImpl.json
devise/abi/DeviseRentalImpl.json
devise/abi/DeviseRentalProxy.json
devise/abi/DeviseToken.json
devise/abi/DeviseTokenSale.json
devise/clients/__init__.py
devise/clients/api.py
devise/clients/client.py
devise/clients/contract.py
devise/clients/token.py
devise/miners/__init__.py
devise/miners/master_node.py
devise/owner/__init__.py
devise/owner/owner.py
devise/owner/token_owner.py