Metadata-Version: 2.1
Name: devise
Version: 1.7.0
Summary: Devise: An Ethereum Marketplace for Engineering Better Representations of Financial Markets
Home-page: https://github.com/devisechain/devise
Maintainer: Devise Foundation
License: GPL-3
Platform: UNKNOWN
Classifier: Development Status :: 4 - Beta
Classifier: Environment :: Console
Classifier: Intended Audience :: Developers
Classifier: License :: OSI Approved :: GNU General Public License v3 (GPLv3)
Classifier: Operating System :: OS Independent
Classifier: Programming Language :: Python
Classifier: Programming Language :: Python :: 3.5
Classifier: Programming Language :: Python :: 3.6
Classifier: Topic :: Software Development :: Libraries
Classifier: Topic :: Office/Business :: Financial :: Investment
Provides-Extra: dev
